scicraft/__init__.py
scicraft-0.0.11.dist-info/licenses/LICENSE
scicraft-0.0.11.dist-info/METADATA
scicraft-0.0.11.dist-info/WHEEL
scicraft-0.0.11.dist-info/top_level.txt
scicraft-0.0.11.dist-info/RECORD
