Metadata-Version: 2.4
Name: SciCraft
Version: 0.0.11
Summary: Simplifying Data Science with Python
Author-email: Jeroen van Raak <j.j.f.vanraak@uva.nl>
License: MIT
Project-URL: Homepage, https://github.com/vanraak/scicraft
Classifier: Programming Language :: Python :: 3
Classifier: License :: OSI Approved :: MIT License
Classifier: Operating System :: OS Independent
Requires-Python: >=3.8
License-File: LICENSE
Dynamic: license-file
